oarepo_dc/__init__.py
oarepo_dc/version.py
oarepo_dc/included_mappings/v7/dcterms-v2.0.0.json
oarepo_dc/jsonschemas/__init__.py
oarepo_dc/jsonschemas/dcterms-v2.0.0.json
oarepo_dc/marshmallow/__init__.py
oarepo_dc-2.2.0.dist-info/LICENSE
oarepo_dc-2.2.0.dist-info/METADATA
oarepo_dc-2.2.0.dist-info/WHEEL
oarepo_dc-2.2.0.dist-info/entry_points.txt
oarepo_dc-2.2.0.dist-info/top_level.txt
oarepo_dc-2.2.0.dist-info/RECORD
