Metadata-Version: 2.1
Name: oarepo-dc
Version: 2.2.0
Summary: DCTerms support for OARepo (just selected props)
Home-page: https://github.com/oarepo/oarepo-dc
Author: Alzbeta Pokorna
Author-email: alzbeta.pokorna@cesnet.cz
License: MIT
Platform: any
Classifier: Environment :: Web Environment
Classifier: Intended Audience :: Developers
Classifier: License :: OSI Approved :: MIT License
Classifier: Operating System :: OS Independent
Classifier: Programming Language :: Python
Classifier: Topic :: Internet :: WWW/HTTP :: Dynamic Content
Classifier: Topic :: Software Development :: Libraries :: Python Modules
Classifier: Programming Language :: Python :: 2
Classifier: Programming Language :: Python :: 2.7
Classifier: Programming Language :: Python :: 3
Classifier: Programming Language :: Python :: 3.5
Classifier: Development Status :: 4 - Beta
Requires-Dist: marshmallow
Requires-Dist: oarepo-multilingual
Requires-Dist: flask
Provides-Extra: tests
Requires-Dist: pytest-invenio[docs] (==1.3.4) ; extra == 'tests'
Requires-Dist: oarepo-multilingual ; extra == 'tests'
Requires-Dist: oarepo-mapping-includes ; extra == 'tests'
Requires-Dist: oarepo[tests] (~=3.3.0) ; extra == 'tests'
Provides-Extra: tests-es7
Requires-Dist: pytest-invenio[docs] (==1.3.4) ; extra == 'tests-es7'
Requires-Dist: oarepo-multilingual ; extra == 'tests-es7'
Requires-Dist: oarepo-mapping-includes ; extra == 'tests-es7'
Requires-Dist: oarepo[tests-es7] (~=3.3.0) ; extra == 'tests-es7'
